{
  "projects": [
    {
      "id": "6bb5",
      "category": {
        "id": "1",
        "name": "Infra"
      },
      "budget": "2000",
      "name": "ffd",
      "cost": 0
    },
    {
      "id": "56fc",
      "name": "tests",
      "budget": "543",
      "category": {
        "id": "3",
        "name": "Design"
      },
      "cost": 0
    },
    {
      "id": "5050",
      "name": "deu certo",
      "budget": "3000",
      "category": {
        "id": "1",
        "name": "Infra"
      },
      "cost": 0
    },
    {
      "id": "2327",
      "name": "deu errado",
      "budget": "3000",
      "category": {
        "id": "4",
        "name": "Planejamento"
      },
      "cost": 0
    },
    {
      "id": "ffb5",
      "name": "teste",
      "budget": "2000",
      "category": {
        "id": "4",
        "name": "Planejamento"
      },
      "cost": 0
    },
    {
      "id": "d7ab",
      "name": "teste",
      "budget": "4000",
      "category": {
        "id": "2",
        "name": "Desenvolvimento"
      },
      "cost": 0
    },
    {
      "id": "f34c",
      "name": "teste",
      "budget": "5000",
      "category": {
        "id": "2",
        "name": "Desenvolvimento"
      },
      "cost": 0
    },
    {
      "id": "d884",
      "name": "teste",
      "budget": "1000",
      "category": {
        "id": "1",
        "name": "Infra"
      },
      "cost": 0
    },
    {
      "id": "6e19",
      "name": "teste",
      "budget": "2000",
      "category": {
        "id": "4",
        "name": "Planejamento"
      },
      "cost": 0
    },
    {
      "id": "29a6",
      "name": "teste",
      "budget": "6000",
      "category": {
        "id": "4",
        "name": "Planejamento"
      },
      "cost": 0
    },
    {
      "id": "f673",
      "name": "teste",
      "budget": "2000",
      "category": {
        "id": "3",
        "name": "Design"
      },
      "cost": 0
    },
    {
      "id": "3985",
      "name": "teste",
      "budget": "2000",
      "category": {
        "id": "1",
        "name": "Infra"
      },
      "cost": 0
    },
    {
      "id": "fe61",
      "name": "carla",
      "budget": "400",
      "category": {
        "id": "3",
        "name": "Design"
      },
      "cost": 0
    }
  ],
  "categories": [
    {
      "id": "1",
      "name": "Infra"
    },
    {
      "id": "2",
      "name": "Desenvolvimento"
    },
    {
      "id": "3",
      "name": "Design"
    },
    {
      "id": "4",
      "name": "Planejamento"
    }
  ]
}